COPYING
MANIFEST.in
NEWS.rst
README
setup.py
uciconfig/__init__.py
uciconfig/errors.py
uciconfig/options.py
uciconfig/parsers.py
uciconfig/registries.py
uciconfig/stacks.py
uciconfig/stores.py
uciconfig.egg-info/PKG-INFO
uciconfig.egg-info/SOURCES.txt
uciconfig.egg-info/dependency_links.txt
uciconfig.egg-info/top_level.txt
uciconfig/tests/__init__.py
uciconfig/tests/test_options.py
uciconfig/tests/test_parsers.py
uciconfig/tests/test_registries.py
uciconfig/tests/test_stacks.py
uciconfig/tests/test_stores.py
uciconfig/tests/test_styles.py