Metadata-Version: 1.0
Name: uciconfig
Version: 0.1.1
Summary: Ubuntu Continuous Integration config framework.
Home-page: https://launchpad.net/uci-config
Author: Vincent Ladeuil
Author-email: vila+ci@canonical.com
License: GPLv3
Platform: UNKNOWN
